geot_cluster.py
geot_cluster-0.9.29.dist-info/DESCRIPTION.rst
geot_cluster-0.9.29.dist-info/METADATA
geot_cluster-0.9.29.dist-info/RECORD
geot_cluster-0.9.29.dist-info/WHEEL
geot_cluster-0.9.29.dist-info/metadata.json
geot_cluster-0.9.29.dist-info/top_level.txt
