Metadata-Version: 2.0
Name: geot-cluster
Version: 0.9.29
Summary: Reasearch project on clustering clients from transaction history
Home-page: https://github.com/LarsWallenstein/Geotrans_cluster
Author: Korsakov Aleksandr
Author-email: corsakov.alex@yandex.ru
License: UNKNOWN
Platform: UNKNOWN
Classifier: Programming Language :: Python :: 3
Classifier: Programming Language :: Python :: 3.6
Classifier: Programming Language :: Python :: 3.7
Classifier: License :: OSI Approved :: MIT License
Classifier: Operating System :: OS Independent
Requires-Dist: folium (>=0.10.1)
Requires-Dist: haversine
Requires-Dist: markov-clustering
Requires-Dist: matplotlib
Requires-Dist: networkx
Requires-Dist: numpy
Requires-Dist: pandas
Requires-Dist: pytest (>=3.7)
Requires-Dist: pytz
Requires-Dist: timezonefinder
